{"trial_id": "00", "hyperparameters": {"space": [{"class_name": "Int", "config": {"name": "units_1", "default": null, "conditions": [], "min_value": 64, "max_value": 256, "step": 32, "sampling": "linear"}}, {"class_name": "Choice", "config": {"name": "activation_1", "default": "relu", "conditions": [], "values": ["relu", "tanh"], "ordered": false}}, {"class_name": "Float", "config": {"name": "l2_1", "default": 1e-05, "conditions": [], "min_value": 1e-05, "max_value": 0.1, "step": null, "sampling": "log"}}, {"class_name": "Int", "config": {"name": "units_2", "default": null, "conditions": [], "min_value": 32, "max_value": 128, "step": 32, "sampling": "linear"}}, {"class_name": "Choice", "config": {"name": "activation_2", "default": "relu", "conditions": [], "values": ["relu", "tanh", "sigmoid"], "ordered": false}}, {"class_name": "Float", "config": {"name": "dropout_rate", "default": 0.1, "conditions": [], "min_value": 0.1, "max_value": 0.5, "step": 0.1, "sampling": "linear"}}, {"class_name": "Int", "config": {"name": "units_3", "default": null, "conditions": [], "min_value": 8, "max_value": 32, "step": 8, "sampling": "linear"}}, {"class_name": "Choice", "config": {"name": "activation_3", "default": "relu", "conditions": [], "values": ["relu", "tanh"], "ordered": false}}, {"class_name": "Float", "config": {"name": "learning_rate", "default": 0.0001, "conditions": [], "min_value": 0.0001, "max_value": 0.01, "step": null, "sampling": "log"}}], "values": {"units_1": 96, "activation_1": "tanh", "l2_1": 0.005469035417925753, "units_2": 64, "activation_2": "relu", "dropout_rate": 0.1, "units_3": 8, "activation_3": "relu", "learning_rate": 0.0015148702467415256}}, "metrics": {"metrics": {"loss": {"direction": "min", "observations": [{"value": [0.0014927353477105498], "step": 13}]}, "rmse": {"direction": "min", "observations": [{"value": [0.0331271979957819], "step": 13}]}, "val_loss": {"direction": "min", "observations": [{"value": [0.001388093747664243], "step": 13}]}, "val_rmse": {"direction": "min", "observations": [{"value": [0.031636327505111694], "step": 13}]}}}, "score": 0.031636327505111694, "best_step": 13, "status": "COMPLETED", "message": null}